django_prometheus/__init__.py
django_prometheus/apps.py
django_prometheus/celery.py
django_prometheus/exports.py
django_prometheus/management.py
django_prometheus/middleware.py
django_prometheus/migrations.py
django_prometheus/models.py
django_prometheus/testutils.py
django_prometheus/urls.py
django_prometheus/utils.py
django_prometheus/cache/__init__.py
django_prometheus/cache/metrics.py
django_prometheus/cache/backends/__init__.py
django_prometheus/cache/backends/django_memcached_consul.py
django_prometheus/cache/backends/filebased.py
django_prometheus/cache/backends/locmem.py
django_prometheus/cache/backends/memcached.py
django_prometheus/cache/backends/redis.py
django_prometheus/db/__init__.py
django_prometheus/db/common.py
django_prometheus/db/metrics.py
django_prometheus/db/backends/__init__.py
django_prometheus/db/backends/mysql/__init__.py
django_prometheus/db/backends/mysql/base.py
django_prometheus/db/backends/postgresql/__init__.py
django_prometheus/db/backends/postgresql/base.py
django_prometheus/db/backends/sqlite3/__init__.py
django_prometheus/db/backends/sqlite3/base.py
django_prometheus/tests/__init__.py
django_prometheus/tests/test_django_prometheus.py
django_prometheus/tests/test_exports.py
django_prometheus/tests/test_testutils.py
django_exporter-2.3.0.dist-info/LICENSE
django_exporter-2.3.0.dist-info/METADATA
django_exporter-2.3.0.dist-info/WHEEL
django_exporter-2.3.0.dist-info/top_level.txt
django_exporter-2.3.0.dist-info/RECORD
