Metadata-Version: 2.1
Name: django-exporter
Version: 2.3.0
Summary: Export Django metrics for Prometheus.
Home-page: http://github.com/prezi/django-exporter
Author: David Guerrero
Author-email: david.guerrero@prezi.com
License: Apache
Keywords: django monitoring prometheus
Classifier: Development Status :: 5 - Production/Stable
Classifier: Intended Audience :: Developers
Classifier: Intended Audience :: Information Technology
Classifier: Intended Audience :: System Administrators
Classifier: Programming Language :: Python :: 2
Classifier: Programming Language :: Python :: 2.7
Classifier: Programming Language :: Python :: 3
Classifier: Programming Language :: Python :: 3.3
Classifier: Programming Language :: Python :: 3.4
Classifier: Programming Language :: Python :: 3.5
Classifier: Programming Language :: Python :: 3.7
Classifier: Programming Language :: Python :: 3.9
Classifier: Framework :: Django
Classifier: Topic :: System :: Monitoring
Classifier: License :: OSI Approved :: Apache Software License
License-File: LICENSE
Requires-Dist: django-redis (<=4.10.0,>=4.8)
Requires-Dist: prometheus-client (<=0.12.0,>=0.5.0)
